uciparse/__init__.py
uciparse/cli.py
uciparse/py.typed
uciparse/uci.py
uciparse-0.3.0.dist-info/METADATA
uciparse-0.3.0.dist-info/WHEEL
uciparse-0.3.0.dist-info/entry_points.txt
uciparse-0.3.0.dist-info/licenses/LICENSE
uciparse-0.3.0.dist-info/licenses/NOTICE
uciparse-0.3.0.dist-info/RECORD
