Metadata-Version: 2.4
Name: uciparse
Version: 0.3.0
Summary: Parse and emit OpenWRT uci-format files
Project-URL: Homepage, https://pypi.org/project/uciparse/
Project-URL: Repository, https://github.com/pronovic/uci-parse
Project-URL: Changelog, https://github.com/pronovic/uci-parse/releases
Project-URL: Documentation, https://uci-parse.readthedocs.io/en/stable/
Project-URL: Issues, https://github.com/pronovic/uci-parse/issues
Author-email: "Kenneth J. Pronovici" <pronovic@ieee.org>
License-Expression: Apache-2.0
License-File: LICENSE
License-File: NOTICE
Classifier: Environment :: Console
Classifier: Intended Audience :: System Administrators
Classifier: Natural Language :: English
Classifier: Operating System :: OS Independent
Classifier: Programming Language :: Python :: 3
Classifier: Programming Language :: Python :: 3.11
Classifier: Programming Language :: Python :: 3.12
Classifier: Programming Language :: Python :: 3.13
Classifier: Programming Language :: Python :: 3.14
Classifier: Topic :: System :: Systems Administration
Requires-Python: <4,>=3.11
Provides-Extra: docs
Requires-Dist: sphinx-autoapi<4.0.0,>=3.3.3; extra == 'docs'
Requires-Dist: sphinx<9.0.0,>=8.1.3; extra == 'docs'
